crd_typed/__init__.py
crd_typed/plugin.py
crd_typed/py.typed
kubernetes-stubs/__init__.pyi
kubernetes-stubs/base/config/__init__.pyi
kubernetes-stubs/base/config/config_exception.pyi
kubernetes-stubs/base/config/dateutil.pyi
kubernetes-stubs/base/config/dateutil_test.pyi
kubernetes-stubs/base/config/exec_provider.pyi
kubernetes-stubs/base/config/exec_provider_test.pyi
kubernetes-stubs/base/config/incluster_config.pyi
kubernetes-stubs/base/config/incluster_config_test.pyi
kubernetes-stubs/base/config/kube_config.pyi
kubernetes-stubs/base/config/kube_config_test.pyi
kubernetes-stubs/base/dynamic/__init__.pyi
kubernetes-stubs/base/dynamic/client.pyi
kubernetes-stubs/base/dynamic/discovery.pyi
kubernetes-stubs/base/dynamic/exceptions.pyi
kubernetes-stubs/base/dynamic/resource.pyi
kubernetes-stubs/base/dynamic/test_client.pyi
kubernetes-stubs/base/dynamic/test_discovery.pyi
kubernetes-stubs/base/hack/boilerplate/boilerplate.pyi
kubernetes-stubs/base/leaderelection/__init__.pyi
kubernetes-stubs/base/leaderelection/electionconfig.pyi
kubernetes-stubs/base/leaderelection/example.pyi
kubernetes-stubs/base/leaderelection/leaderelection.pyi
kubernetes-stubs/base/leaderelection/leaderelection_test.pyi
kubernetes-stubs/base/leaderelection/leaderelectionrecord.pyi
kubernetes-stubs/base/leaderelection/resourcelock/__init__.pyi
kubernetes-stubs/base/leaderelection/resourcelock/configmaplock.pyi
kubernetes-stubs/base/stream/__init__.pyi
kubernetes-stubs/base/stream/stream.pyi
kubernetes-stubs/base/stream/ws_client.pyi
kubernetes-stubs/base/stream/ws_client_test.pyi
kubernetes-stubs/base/watch/__init__.pyi
kubernetes-stubs/base/watch/watch.pyi
kubernetes-stubs/base/watch/watch_test.pyi
kubernetes-stubs/client/__init__.pyi
kubernetes-stubs/client/api_client.pyi
kubernetes-stubs/client/configuration.pyi
kubernetes-stubs/client/exceptions.pyi
kubernetes-stubs/client/rest.pyi
kubernetes-stubs/client/api/__init__.pyi
kubernetes-stubs/client/api/admissionregistration_api.pyi
kubernetes_typed-18.20.2.dist-info/LICENSE
kubernetes_typed-18.20.2.dist-info/METADATA
kubernetes_typed-18.20.2.dist-info/WHEEL
kubernetes_typed-18.20.2.dist-info/top_level.txt
kubernetes_typed-18.20.2.dist-info/RECORD
