Metadata-Version: 2.1
Name: kubernetes-typed
Version: 18.20.2
Summary: Collection of mypy plugins and stubs for kubernetes
Home-page: https://github.com/gordonbondon/kubernetes-typed
Author: Artem Yarmoliuk
License: Apache License Version 2.0
Project-URL: Bug Reports, https://github.com/gordonbondon/kubernetes-typed/issues
Project-URL: Source, https://github.com/gordonbondon/kubernetes-typed
Keywords: Kubernetes,MyPy,Stubs,Typing
Classifier: Development Status :: 4 - Beta
Classifier: Environment :: Console
Classifier: Environment :: Plugins
Classifier: Intended Audience :: Developers
Classifier: License :: OSI Approved :: Apache Software License
Classifier: Programming Language :: Python :: 3
Classifier: Programming Language :: Python :: 3.8
Classifier: Programming Language :: Python :: 3.9
Classifier: Programming Language :: Python :: 3.10
Classifier: Programming Language :: Python :: 3.11
Classifier: Programming Language :: Python :: 3.12
Classifier: Programming Language :: Python :: 3 :: Only
Classifier: Topic :: Software Development
Classifier: Typing :: Typed
Requires-Python: >=3.8
License-File: LICENSE
Requires-Dist: jsonschema-typed-v2
Requires-Dist: jsonschema<4.18
Requires-Dist: mypy>=1.9.0
Requires-Dist: mypy-extensions>=1.0.0
Requires-Dist: PyYAML
Provides-Extra: client
Requires-Dist: kubernetes; extra == "client"
Provides-Extra: dev
Requires-Dist: black; extra == "dev"
Requires-Dist: gitpython==3.1.43; extra == "dev"
Requires-Dist: isort; extra == "dev"
Requires-Dist: flake8; extra == "dev"
Requires-Dist: flake8-black; extra == "dev"
Requires-Dist: flake8-isort; extra == "dev"
Requires-Dist: jinja2; extra == "dev"
Requires-Dist: pytest; extra == "dev"
Requires-Dist: tox; extra == "dev"
Requires-Dist: tox-gh-actions; extra == "dev"
Requires-Dist: wemake-python-styleguide; extra == "dev"
